pytest_yamltree.py
pytest_yamltree-0.1.2.dist-info/LICENSE
pytest_yamltree-0.1.2.dist-info/METADATA
pytest_yamltree-0.1.2.dist-info/WHEEL
pytest_yamltree-0.1.2.dist-info/entry_points.txt
pytest_yamltree-0.1.2.dist-info/top_level.txt
pytest_yamltree-0.1.2.dist-info/RECORD
