Metadata-Version: 2.1
Name: pytest-yamltree
Version: 0.1.2
Summary: Create or check file/directory trees described by YAML
Home-page: https://github.com/MarSoft/pytest-yamltree
Author: Semyon Maryasin
Author-email: simeon@maryasin.name
Maintainer: Semyon Maryasin
Maintainer-email: simeon@maryasin.name
License: MIT
Platform: UNKNOWN
Classifier: Development Status :: 4 - Beta
Classifier: Framework :: Pytest
Classifier: Intended Audience :: Developers
Classifier: Topic :: Software Development :: Testing
Classifier: Programming Language :: Python
Classifier: Programming Language :: Python :: 2
Classifier: Programming Language :: Python :: 2.7
Classifier: Programming Language :: Python :: 3
Classifier: Programming Language :: Python :: 3.5
Classifier: Programming Language :: Python :: 3.6
Classifier: Programming Language :: Python :: 3.7
Classifier: Programming Language :: Python :: 3.8
Classifier: Programming Language :: Python :: Implementation :: CPython
Classifier: Programming Language :: Python :: Implementation :: PyPy
Classifier: Operating System :: OS Independent
Classifier: License :: OSI Approved :: MIT License
Requires-Dist: pytest (>=3.1.1)
Requires-Dist: pyyaml
